psychopy_mri_emulator/__init__.py
psychopy_mri_emulator/emulator.py
psychopy_mri_emulator-0.0.2.dist-info/LICENSE
psychopy_mri_emulator-0.0.2.dist-info/METADATA
psychopy_mri_emulator-0.0.2.dist-info/WHEEL
psychopy_mri_emulator-0.0.2.dist-info/entry_points.txt
psychopy_mri_emulator-0.0.2.dist-info/top_level.txt
psychopy_mri_emulator-0.0.2.dist-info/RECORD
