Metadata-Version: 2.1
Name: psychopy-mri-emulator
Version: 0.0.2
Summary: Software emulator for fMRI machines.
Author: Jeremy Gray
Author-email: Jon Peirce <jon@opensceincetools.org>, Matthew Cutone <mcutone@opensceincetools.org>, Todd Parsons <todd@opensceincetools.org>
License: GNU General Public License v3 (GPLv3)
Project-URL: homepage, https://github.com/psychopy/psychopy-mri-emulator
Project-URL: repository, https://github.com/psychopy/psychopy-mri-emulator
Project-URL: changelog, https://github.com/psychopy/psychopy-mri-emulator/blob/main/CHANGELOG.md
Requires-Python: >=3.7
License-File: LICENSE
Provides-Extra: docs
Requires-Dist: psychopy ; extra == 'docs'
Requires-Dist: sphinx ; extra == 'docs'
Requires-Dist: furo ; extra == 'docs'
Provides-Extra: tests
Requires-Dist: psychopy ; extra == 'tests'
Requires-Dist: pytest ; extra == 'tests'
